{
	"inputs" : 
	[
		{
			"path" : "CMakeLists.txt"
		},
		{
			"isGenerated" : true,
			"path" : "build/CMakeFiles/3.24.1/CMakeSystem.cmake"
		},
		{
			"isCMake" : true,
			"isExternal" : true,
			"path" : "/usr/local/Cellar/cmake/3.24.1/share/cmake/Modules/CMakeSystemSpecificInitialize.cmake"
		},
		{
			"isCMake" : true,
			"isExternal" : true,
			"path" : "/usr/local/Cellar/cmake/3.24.1/share/cmake/Modules/Platform/Darwin-Initialize.cmake"
		},
		{
			"isGenerated" : true,
			"path" : "build/CMakeFiles/3.24.1/CMakeCCompiler.cmake"
		},
		{
			"isCMake" : true,
			"isExternal" : true,
			"path" : "/usr/local/Cellar/cmake/3.24.1/share/cmake/Modules/CMakeSystemSpecificInformation.cmake"
		},
		{
			"isCMake" : true,
			"isExternal" : true,
			"path" : "/usr/local/Cellar/cmake/3.24.1/share/cmake/Modules/CMakeGenericSystem.cmake"
		},
		{
			"isCMake" : true,
			"isExternal" : true,
			"path" : "/usr/local/Cellar/cmake/3.24.1/share/cmake/Modules/CMakeInitializeConfigs.cmake"
		},
		{
			"isCMake" : true,
			"isExternal" : true,
			"path" : "/usr/local/Cellar/cmake/3.24.1/share/cmake/Modules/Platform/Darwin.cmake"
		},
		{
			"isCMake" : true,
			"isExternal" : true,
			"path" : "/usr/local/Cellar/cmake/3.24.1/share/cmake/Modules/Platform/UnixPaths.cmake"
		},
		{
			"isCMake" : true,
			"isExternal" : true,
			"path" : "/usr/local/Cellar/cmake/3.24.1/share/cmake/Modules/CMakeCInformation.cmake"
		},
		{
			"isCMake" : true,
			"isExternal" : true,
			"path" : "/usr/local/Cellar/cmake/3.24.1/share/cmake/Modules/CMakeLanguageInformation.cmake"
		},
		{
			"isCMake" : true,
			"isExternal" : true,
			"path" : "/usr/local/Cellar/cmake/3.24.1/share/cmake/Modules/Compiler/GNU-C.cmake"
		},
		{
			"isCMake" : true,
			"isExternal" : true,
			"path" : "/usr/local/Cellar/cmake/3.24.1/share/cmake/Modules/Compiler/GNU.cmake"
		},
		{
			"isCMake" : true,
			"isExternal" : true,
			"path" : "/usr/local/Cellar/cmake/3.24.1/share/cmake/Modules/Compiler/CMakeCommonCompilerMacros.cmake"
		},
		{
			"isCMake" : true,
			"isExternal" : true,
			"path" : "/usr/local/Cellar/cmake/3.24.1/share/cmake/Modules/Platform/Apple-GNU-C.cmake"
		},
		{
			"isCMake" : true,
			"isExternal" : true,
			"path" : "/usr/local/Cellar/cmake/3.24.1/share/cmake/Modules/Platform/Apple-GNU.cmake"
		},
		{
			"isCMake" : true,
			"isExternal" : true,
			"path" : "/usr/local/Cellar/cmake/3.24.1/share/cmake/Modules/CMakeCommonLanguageInclude.cmake"
		},
		{
			"isGenerated" : true,
			"path" : "build/CMakeFiles/3.24.1/CMakeASMCompiler.cmake"
		},
		{
			"isCMake" : true,
			"isExternal" : true,
			"path" : "/usr/local/Cellar/cmake/3.24.1/share/cmake/Modules/CMakeASMInformation.cmake"
		},
		{
			"isCMake" : true,
			"isExternal" : true,
			"path" : "/usr/local/Cellar/cmake/3.24.1/share/cmake/Modules/Compiler/GNU-ASM.cmake"
		},
		{
			"isCMake" : true,
			"isExternal" : true,
			"path" : "/usr/local/Cellar/cmake/3.24.1/share/cmake/Modules/Compiler/GNU.cmake"
		},
		{
			"path" : "source/boot/CMakeLists.txt"
		},
		{
			"path" : "source/loader/CMakeLists.txt"
		}
	],
	"kind" : "cmakeFiles",
	"paths" : 
	{
		"build" : "/Users/bytedance/Documents/os/30dayos/raw/build",
		"source" : "/Users/bytedance/Documents/os/30dayos/raw"
	},
	"version" : 
	{
		"major" : 1,
		"minor" : 0
	}
}
